keras_rs/__init__.py
keras_rs/layers/__init__.py
keras_rs/losses/__init__.py
keras_rs/metrics/__init__.py
keras_rs/src/__init__.py
keras_rs/src/api_export.py
keras_rs/src/types.py
keras_rs/src/version.py
keras_rs/src/layers/__init__.py
keras_rs/src/layers/embedding/__init__.py
keras_rs/src/layers/embedding/base_distributed_embedding.py
keras_rs/src/layers/embedding/distributed_embedding.py
keras_rs/src/layers/embedding/distributed_embedding_config.py
keras_rs/src/layers/embedding/embed_reduce.py
keras_rs/src/layers/embedding/jax/__init__.py
keras_rs/src/layers/embedding/jax/checkpoint_utils.py
keras_rs/src/layers/embedding/jax/config_conversion.py
keras_rs/src/layers/embedding/jax/distributed_embedding.py
keras_rs/src/layers/embedding/jax/embedding_lookup.py
keras_rs/src/layers/embedding/jax/embedding_utils.py
keras_rs/src/layers/embedding/tensorflow/__init__.py
keras_rs/src/layers/embedding/tensorflow/config_conversion.py
keras_rs/src/layers/embedding/tensorflow/distributed_embedding.py
keras_rs/src/layers/feature_interaction/__init__.py
keras_rs/src/layers/feature_interaction/dot_interaction.py
keras_rs/src/layers/feature_interaction/feature_cross.py
keras_rs/src/layers/retrieval/__init__.py
keras_rs/src/layers/retrieval/brute_force_retrieval.py
keras_rs/src/layers/retrieval/hard_negative_mining.py
keras_rs/src/layers/retrieval/remove_accidental_hits.py
keras_rs/src/layers/retrieval/retrieval.py
keras_rs/src/layers/retrieval/sampling_probability_correction.py
keras_rs/src/losses/__init__.py
keras_rs/src/losses/pairwise_hinge_loss.py
keras_rs/src/losses/pairwise_logistic_loss.py
keras_rs/src/losses/pairwise_loss.py
keras_rs/src/losses/pairwise_loss_utils.py
keras_rs/src/losses/pairwise_mean_squared_error.py
keras_rs/src/losses/pairwise_soft_zero_one_loss.py
keras_rs/src/metrics/__init__.py
keras_rs/src/metrics/dcg.py
keras_rs/src/metrics/mean_average_precision.py
keras_rs/src/metrics/mean_reciprocal_rank.py
keras_rs/src/metrics/ndcg.py
keras_rs-0.3.0.dist-info/METADATA
keras_rs-0.3.0.dist-info/WHEEL
keras_rs-0.3.0.dist-info/top_level.txt
keras_rs-0.3.0.dist-info/RECORD
