Metadata-Version: 2.4
Name: keras-rs
Version: 0.3.0
Summary: Multi-backend recommender systems with Keras 3.
Author-email: Keras team <keras-users@googlegroups.com>
License: Apache License 2.0
Project-URL: Home, https://keras.io/keras_rs
Project-URL: Repository, https://github.com/keras-team/keras-rs
Classifier: Development Status :: 3 - Alpha
Classifier: Programming Language :: Python :: 3
Classifier: Programming Language :: Python :: 3.11
Classifier: Programming Language :: Python :: 3.12
Classifier: Programming Language :: Python :: 3.13
Classifier: Programming Language :: Python :: 3 :: Only
Classifier: Operating System :: Unix
Classifier: Operating System :: Microsoft :: Windows
Classifier: Operating System :: MacOS
Classifier: Intended Audience :: Science/Research
Classifier: Topic :: Scientific/Engineering
Classifier: Topic :: Software Development
Requires-Python: >=3.11
Requires-Dist: keras
Requires-Dist: ml-dtypes
